{
"spotifyArtists":[
{
"name":"BTS",
"id": "3Nrfpe0tUJi4K4DXYWgMUX"
},
{
"name":"TXT",
"id": "0ghlgldX5Dd6720Q3qFyQB"
},
{
"name":"Ariana Grande",
"id": "66CXWjxzNUsdJxJ2JdwvnR"
},
{
"name":"Selena Gomez",
"id": "0C8ZW7ezQVs4URX5aX7Kqx"
},
{
"name":"G-Eazy",
"id": "02kJSzxNuaWGqwubyUba0Z"
},
{
"name":"Twenty One Pilots",
"id": "3YQKmKGau1PzlVlkL1iodx"
},
{
"name":"Halsey",
"id": "26VFTg2z8YR0cCuwLzESi2"
},
{
"name":"Alessia Cara",
"id": "2wUjUUtkb5lvLKcGKsKqsR"
},
{
"name":"The Chainsmokers",
"id": "69GGBxA162lTqCwzJG5jLp"
},
{
"name":"Justin Beiber",
"id": "1uNFoZAHBGtllmzznpCI3s"
},
{
"name":"Vance Joy",
"id": "10exVja0key0uqUkk6LJRT"
},
{
"name":"George Ezra",
"id": "2ysnwxxNtSgbb9t1m2Ur4j"
},
{
"name":"Panic! At The Disco ",
"id": "20JZFwl6HVl6yg8a4H3ZqK"
},

{
"name":"The Beatles",
"id": "3WrFJ7ztbogyGnTHbHJFl2"
},
{
"name":"Baekhyun",
"id": "4ufh0WuMZh6y4Dmdnklvdl"
},
{
"name":"Black Pink",
"id": "41MozSoPIsD1dJM0CLPjZF"
},
{
"name":"HOSHI",
"id": "6nWKAdMv1BDq1zHfZzkdbR"
},
{
"name":"ENYPHEN",
"id": "5t5FqBwTcgKTaWmfEbwQY9"
},

{
"name":"NCT U",
"id": "3paGCCtX1Xr4Gx53mSeZuQ"
},
{
"name":"Jason Derulo",
"id": "07YZf4WDAMNwqr4jfgOZ8y"
},
{
"name":"Becky G",
"id": "4obzFoKoKRHIphyHzJ35G3"
},
{
"name":"KAI",
"id": "6iVo62B0bdTknRcrktCmak"
},
{
"name":"Bad Bunny",
"id": "4q3ewBCX7sLwd24euuV69X"
},
{
"name":"Ozuna",
"id": "1i8SpTcr7yvPOmcqrbnVXY"
},
{
"name":"J Balvin",
"id": "1vyhD5VmyZ7KMfW5gqLgo5"
},
{
"name":"Maluma",
"id": "1r4hJ1h58CWwUQe3MxPuau"
},
{
"name":"Cardi B",
"id": "4kYSro6naA4h99UJvo89HB"
},
{
"name":"Snoop Dog",
"id": "7hJcb9fa4alzcOq3EaNPoG"
},
{
"name":"blackbear",
"id": "2cFrymmkijnjDg9SS92EPM"
},
{
"name":"Billie Eilish",
"id": "6qqNVTkY8uBg9cP3Jd7DAH"
},
{
"name":"The Neighbourhood",
"id": "77SW9BnxLY8rJ0RciFqkHh"
},
{
"name":"6LACK",
"id": "4IVAbR2w4JJNJDDRFP3E83"
},
{
"name":"Lady Gaga",
"id": "1HY2Jd0NmPuamShAr6KMms"
},
{
"name":"Calibre 50",
"id": "4jogXSSvlyMkODGSZ2wc2P"
},
{
"name":"Ulices Chaidez",
"id": "5npvUMe1CGnIhTX7OaLGVV"
}

]	
}
